modeldemo/__init__.py
modeldemo/icon.png
modeldemo/sound.wav
modeldemo/utils.py
modeldemo-0.24.0.dist-info/METADATA
modeldemo-0.24.0.dist-info/WHEEL
modeldemo-0.24.0.dist-info/entry_points.txt
modeldemo-0.24.0.dist-info/licenses/LICENSE
modeldemo-0.24.0.dist-info/RECORD
