Metadata-Version: 2.3
Name: modeldemo
Version: 0.24.0
Summary: TBD
License-File: LICENSE
Requires-Python: >=3.12
Requires-Dist: accelerate>=0.34.2
Requires-Dist: huggingface-hub>=0.24.7
Requires-Dist: mss>=9.0.2
Requires-Dist: notify-py>=0.3.43
Requires-Dist: pre-commit>=3.8.0
Requires-Dist: timm>=1.0.9
Requires-Dist: torch>=2.4.1
Requires-Dist: transformers>=4.44.2
Requires-Dist: typer>=0.12.5
Provides-Extra: gpu
Requires-Dist: bitsandbytes>=0.43.3; extra == 'gpu'
Requires-Dist: flash-attn>=2.6.3; extra == 'gpu'
